error_cats.py
Error_Cats-0.1.0.dist-info/LICENSE
Error_Cats-0.1.0.dist-info/METADATA
Error_Cats-0.1.0.dist-info/WHEEL
Error_Cats-0.1.0.dist-info/top_level.txt
Error_Cats-0.1.0.dist-info/RECORD
